scrapy_redis/__init__.py
scrapy_redis/connection.py
scrapy_redis/defaults.py
scrapy_redis/dupefilter.py
scrapy_redis/picklecompat.py
scrapy_redis/pipelines.py
scrapy_redis/queue.py
scrapy_redis/scheduler.py
scrapy_redis/spiders.py
scrapy_redis/stats.py
scrapy_redis/utils.py
scrapy_redis-0.9.1.dist-info/AUTHORS.rst
scrapy_redis-0.9.1.dist-info/LICENSE
scrapy_redis-0.9.1.dist-info/METADATA
scrapy_redis-0.9.1.dist-info/WHEEL
scrapy_redis-0.9.1.dist-info/top_level.txt
scrapy_redis-0.9.1.dist-info/RECORD
