Metadata-Version: 2.1
Name: scrapy-redis
Version: 0.9.1
Summary: Redis-based components for Scrapy.
Home-page: https://github.com/rmax/scrapy-redis
Author: R Max Espinoza
Author-email: hey@rmax.dev
License: MIT
Keywords: scrapy-redis
Classifier: Development Status :: 4 - Beta
Classifier: Intended Audience :: Developers
Classifier: License :: OSI Approved :: MIT License
Classifier: Natural Language :: English
Classifier: Programming Language :: Python :: 3
Classifier: Programming Language :: Python :: 3.7
Classifier: Programming Language :: Python :: 3.8
Classifier: Programming Language :: Python :: 3.9
Classifier: Programming Language :: Python :: 3.10
License-File: LICENSE
License-File: AUTHORS.rst
Requires-Dist: scrapy>=2.6.0
Requires-Dist: redis>=4.2
Requires-Dist: six>=1.15
